konduto/__init__.py
konduto/api/__init__.py
konduto/api/clients/__init__.py
konduto/api/clients/v1/__init__.py
konduto/api/clients/v1/order.py
konduto/api/clients/v1/restrict_list.py
konduto/api/resources/__init__.py
konduto/api/resources/konduto_address.py
konduto/api/resources/konduto_customer.py
konduto/api/resources/konduto_order_status.py
konduto/api/resources/konduto_payment.py
konduto/api/resources/konduto_seller.py
konduto/api/resources/konduto_shopping_cart.py
konduto/api/resources/kondutotravel.py
konduto/api/resources/requests/__init__.py
konduto/api/resources/requests/konduto_order_request.py
konduto/api/resources/requests/konduto_order_status_request.py
konduto/api/resources/requests/konduto_restrict_email_request.py
konduto/api/resources/response/__init__.py
konduto/api/resources/response/konduto_error.py
konduto/api/resources/response/konduto_order_response.py
konduto/api/resources/response/restrict_email_response.py
konduto/client.py
konduto/infrastructure/__init__.py
konduto/infrastructure/either.py
konduto/infrastructure/json_enconder.py
konduto/infrastructure/parsers.py
konduto_sdk-1.0.0.dist-info/LICENSE
konduto_sdk-1.0.0.dist-info/WHEEL
konduto_sdk-1.0.0.dist-info/METADATA
konduto_sdk-1.0.0.dist-info/RECORD
