Metadata-Version: 2.1
Name: konduto-sdk
Version: 1.0.0
Summary: SDK to let the process easier to integrate your application with konduto rest API
Home-page: https://github.com/alefhsousa/konduto-sdk
License: MIT
Keywords: konduto,sdk,api,konduto SDK
Author: Alefh Sousa
Author-email: alefh.sousa@gmail.com
Requires-Python: >=3.6,<4.0
Classifier: Development Status :: 5 - Production/Stable
Classifier: Environment :: Web Environment
Classifier: Intended Audience :: Developers
Classifier: License :: OSI Approved :: MIT License
Classifier: Operating System :: OS Independent
Classifier: Programming Language :: Python :: 3
Classifier: Programming Language :: Python :: 3.6
Classifier: Programming Language :: Python :: 3.7
Classifier: Programming Language :: Python :: 3.8
Classifier: Topic :: Internet :: WWW/HTTP :: Dynamic Content
Classifier: Topic :: Software Development :: Libraries :: Python Modules
Requires-Dist: dacite (>=1.3.0,<2.0.0)
Requires-Dist: requests (>=2.16.0,<3.0.0)
Project-URL: Repository, https://github.com/alefhsousa/konduto-sdk
